chml/__init__.py
chml/frp/__init__.py
chml/frp/frpc.exe
chml/frp/frpc.ini
chml/frp/frpc_full.ini
chml/frp/frps.exe
chml/frp/frps.ini
chml/frp/frps_full.ini
chml/frp/LICENSE
chml/main.py
chml-0.0.6.dist-info/entry_points.txt
chml-0.0.6.dist-info/METADATA
chml-0.0.6.dist-info/WHEEL
chml-0.0.6.dist-info/RECORD
