Metadata-Version: 2.3
Name: chml
Version: 0.0.6
Summary: Frp client configuration and running tool.
License: MIT
Keywords: frp,client,configuration,tunnel
Author: Your Name
Author-email: your.email@example.com
Requires-Python: >=3.7
Classifier: Development Status :: 3 - Alpha
Classifier: Intended Audience :: Developers
Classifier: Topic :: System :: Networking
Classifier: License :: OSI Approved :: MIT License
Classifier: Programming Language :: Python :: 3
Classifier: Programming Language :: Python :: 3.7
Classifier: Programming Language :: Python :: 3.8
Classifier: Programming Language :: Python :: 3.9
Classifier: Programming Language :: Python :: 3.10
Classifier: Programming Language :: Python :: 3.11
Classifier: Programming Language :: Python :: 3.12
Requires-Dist: httpx
Requires-Dist: inquirerpy
Requires-Dist: pyyaml
Requires-Dist: rich
Requires-Dist: typer
Project-URL: Documentation, https://github.com/drizzlexlh/chmlfrp-cli/blob/main/README.md
Project-URL: Homepage, https://github.com/drizzlexlh/chmlfrp-cli
Project-URL: Repository, https://github.com/drizzlexlh/chmlfrp-cli
